setup.py
softinfo.py
softinfo.egg-info/PKG-INFO
softinfo.egg-info/SOURCES.txt
softinfo.egg-info/dependency_links.txt
softinfo.egg-info/top_level.txt