Metadata-Version: 1.0
Name: softinfo
Version: 0.2
Summary: For scan software info package
Home-page: https://github.com/523144419/autoScan4CMDB
Author: 523144419
Author-email: 523144419@qq.com
License: UNKNOWN
Platform: UNKNOWN
